badger/__init__.py
badger/__main__.py
badger/version.py
badger/fonts/DejaVuSans.ttf
badger/templates/flat.svg
badger-0.1.2.dist-info/DESCRIPTION.rst
badger-0.1.2.dist-info/METADATA
badger-0.1.2.dist-info/RECORD
badger-0.1.2.dist-info/WHEEL
badger-0.1.2.dist-info/entry_points.txt
badger-0.1.2.dist-info/metadata.json
badger-0.1.2.dist-info/top_level.txt
badger-0.1.2.dist-info/zip-safe
