Metadata-Version: 2.0
Name: badger
Version: 0.1.2
Summary: Commandline Interface to create shields.io style badges as SVG.
Home-page: https://github.com/Tethik/badger
Author: Joakim Uddholm
Author-email: tethik@gmail.com
License: MIT License
Requires-Dist: freetype-py
